.gitignore
.travis.yml
README.md
requirements.txt
requirements_dev.txt
requirements_test.txt
setup.cfg
setup.py
src/tabla/__init__.py
src/tabla/_version.py
src/tabla/tabla.py
src/tabla.egg-info/PKG-INFO
src/tabla.egg-info/SOURCES.txt
src/tabla.egg-info/dependency_links.txt
src/tabla.egg-info/requires.txt
src/tabla.egg-info/top_level.txt
src/tabla.egg-info/zip-safe
tests/tabla/test_tabla.py