Metadata-Version: 2.1
Name: tabla
Version: 0.0.1
Summary: Generate LaTeX tables with Python
Home-page: https://github.com/ryanjdillon/tabla
Author: Ryan J. Dillon
Author-email: ryanjamesdillon@gmail.com
License: GPL-3.0+
Keywords: LaTeX,puclication,tables
Platform: UNKNOWN
Classifier: Development Status :: 3 - Alpha
Classifier: Intended Audience :: Science/Research
Classifier: Programming Language :: Python :: 3.6
Classifier: Programming Language :: Python :: 3.7
